[
  {
    "line": 2,
    "elements": [
      {
        "line": 7,
        "name": "common steps",
        "description": "",
        "type": "background",
        "keyword": "Background",
        "steps": [
          {
            "result": {
              "duration": 1072000000,
              "status": "passed"
            },
            "line": 8,
            "name": "user is on the login page",
            "match": {
              "location": "com.vytrack.step_definitions.LoginStepDefinitions.user_is_on_the_login_page()"
            },
            "keyword": "Given "
          }
        ]
      },
      {
        "start_timestamp": "2020-11-09T19:30:38.747Z",
        "before": [
          {
            "result": {
              "duration": 7428000000,
              "status": "passed"
            },
            "match": {
              "location": "com.vytrack.step_definitions.Hooks.setup(io.cucumber.java.Scenario)"
            }
          }
        ],
        "line": 40,
        "name": "Invalid password",
        "description": "",
        "id": "as-user-i-want-to-be-able-to-login-under-different-roles;invalid-password",
        "after": [
          {
            "result": {
              "duration": 851000000,
              "status": "passed"
            },
            "match": {
              "location": "com.vytrack.step_definitions.Hooks.tearDown()"
            }
          }
        ],
        "type": "scenario",
        "keyword": "Scenario",
        "steps": [
          {
            "result": {
              "duration": 1222000000,
              "status": "passed"
            },
            "line": 41,
            "name": "user logs in with \"storemanager85\" username and \"wrong\" password",
            "match": {
              "arguments": [
                {
                  "val": "\"storemanager85\"",
                  "offset": 18
                },
                {
                  "val": "\"wrong\"",
                  "offset": 48
                }
              ],
              "location": "com.vytrack.step_definitions.LoginStepDefinitions.user_logs_in_with_username_and_password(java.lang.String,java.lang.String)"
            },
            "keyword": "When "
          },
          {
            "result": {
              "error_message": "org.junit.ComparisonFailure: expected:\u003cInvalid [] name or password.\u003e but was:\u003cInvalid [user] name or password.\u003e\r\n\tat org.junit.Assert.assertEquals(Assert.java:117)\r\n\tat org.junit.Assert.assertEquals(Assert.java:146)\r\n\tat com.vytrack.step_definitions.LoginStepDefinitions.user_verifies_that_message_is_displayed(LoginStepDefinitions.java:61)\r\n\tat ✽.user verifies that \"Invalid  name or password.\" message is displayed(file:///C:/IdeaProjects/Vytrack/src/test/resources/features/Login.feature:42)\r\n",
              "duration": 5050000000,
              "status": "failed"
            },
            "line": 42,
            "name": "user verifies that \"Invalid  name or password.\" message is displayed",
            "match": {
              "arguments": [
                {
                  "val": "\"Invalid  name or password.\"",
                  "offset": 19
                }
              ],
              "location": "com.vytrack.step_definitions.LoginStepDefinitions.user_verifies_that_message_is_displayed(java.lang.String)"
            },
            "keyword": "Then "
          }
        ],
        "tags": [
          {
            "name": "@login"
          },
          {
            "name": "@negative_login"
          }
        ]
      }
    ],
    "name": "As user I want to be able to login under different roles",
    "description": "",
    "id": "as-user-i-want-to-be-able-to-login-under-different-roles",
    "keyword": "Feature",
    "uri": "file:src/test/resources/features/Login.feature",
    "tags": [
      {
        "name": "@login",
        "type": "Tag",
        "location": {
          "line": 1,
          "column": 1
        }
      }
    ]
  }
]